amas/AMAS.py
amas/__init__.py
amas-1.0.dist-info/LICENSE.md
amas-1.0.dist-info/METADATA
amas-1.0.dist-info/WHEEL
amas-1.0.dist-info/top_level.txt
amas-1.0.dist-info/RECORD
