Metadata-Version: 2.1
Name: amas
Version: 1.0
Summary: Calculate various summary statistics on a multiple sequence alignment
Home-page: https://github.com/marekborowiec/AMAS
Author: Marek Borowiec
Author-email: petiolus@gmail.com
License: GNU PL v3
Keywords: amas
Platform: UNKNOWN
Classifier: Development Status :: 2 - Pre-Alpha
Classifier: Intended Audience :: Developers
Classifier: License :: OSI Approved :: GNU General Public License v3 (GPLv3)
Classifier: Natural Language :: English
Classifier: Programming Language :: Python :: 3.3
